pebba/__init__.py
pebba/__main__.py
pebba/analysis/ORA.py
pebba/analysis/ORA_hyperparameter_exploration.py
pebba/analysis/__init__.py
pebba/analysis/auxiliary_analysis.py
pebba/analysis/top_genes.py
pebba/main.py
pebba/utils/__init__.py
pebba/utils/deg_utils.py
pebba/utils/gmt_utils.py
pebba/visualization.py
pebba-0.1.3.dist-info/LICENSE
pebba-0.1.3.dist-info/WHEEL
pebba-0.1.3.dist-info/METADATA
pebba-0.1.3.dist-info/RECORD
