Metadata-Version: 2.1
Name: pebba
Version: 0.1.3
Summary: A tool for ORA meta-analysis
Home-page: https://pebba.sysbio.tools/
License: GPL-3.0-or-later
Author: Alan Barzilay
Requires-Python: >=3.8,<3.11
Classifier: License :: OSI Approved :: GNU General Public License v3 or later (GPLv3+)
Classifier: Programming Language :: Python :: 3
Classifier: Programming Language :: Python :: 3.10
Classifier: Programming Language :: Python :: 3.8
Classifier: Programming Language :: Python :: 3.9
Requires-Dist: numpy (>=1.23.1,<2.0.0)
Requires-Dist: pandas (>=1.4.3,<2.0.0)
Requires-Dist: plotly (>=5.9.0,<6.0.0)
Requires-Dist: scipy (>=1.8.1,<2.0.0)
Requires-Dist: statsmodels (>=0.13.2,<0.14.0)
Project-URL: Repository, https://github.com/csbl-br/pebba
